{
  "conditions": [
    {
      "modid": "alexscaves",
      "type": "forge:mod_loaded"
    }
  ],
  "entity": "alexscaves:gloomoth",
  "variants": [],
  "name": "entity.alexscaves.gloomoth",
  "name_color": "#DADADA",
  "gui_scale": 1,
  "gui_x_offset": 0,
  "gui_y_offset": 0,
  "gui_z_offset": 0,
  "sim_cost": 64,
  "input": {
    "item": "hostilenetworks:prediction_matrix"
  },
  "base_drop": {
    "item": "hostilenetworks:overworld_prediction"
  },
  "trivia": "hostilenetworks.trivia.gloomoth",
  "fabricator_drops": [
    {
      "item": "alexscaves:moth_dust",
      "count": 2
    }
  ],
  "tier_data": [8, 76, 256, 529],
  "data_per_kill": [1, 2, 3, 4]
}
